goplus/__init__.py
goplus/__version__.py
goplus/address.py
goplus/approve.py
goplus/auth.py
goplus/base.py
goplus/chain.py
goplus/dapp.py
goplus/decode.py
goplus/errorcode.py
goplus/locker.py
goplus/nft.py
goplus/phishing_site.py
goplus/rug_pull.py
goplus/token.py
goplus/tx_simulation.py
goplus-0.2.5.dist-info/licenses/LICENSE
swagger_client/__init__.py
swagger_client/api_client.py
swagger_client/configuration.py
swagger_client/rest.py
swagger_client/api/__init__.py
swagger_client/api/approve_controller_v_1_api.py
swagger_client/api/approve_controller_v_2_api.py
swagger_client/api/contract_abi_controller_api.py
swagger_client/api/dapp_controller_api.py
swagger_client/api/defi_controller_api.py
swagger_client/api/lock_controller_api.py
swagger_client/api/nft_controller_api.py
swagger_client/api/token_controller_api.py
swagger_client/api/token_controller_v_1_api.py
swagger_client/api/token_security_api_for_solana__beta_api.py
swagger_client/api/token_security_api_for_sui_api.py
swagger_client/api/transaction_simulation_for_solana_api.py
swagger_client/api/website_controller_api.py
swagger_client/models/__init__.py
swagger_client/models/abi_address_info.py
swagger_client/models/abi_param_info.py
swagger_client/models/approve_address_info.py
swagger_client/models/approve_erc1155_result.py
swagger_client/models/approve_nft1155_list_response.py
swagger_client/models/approve_nft_list_response.py
swagger_client/models/approve_result.py
swagger_client/models/approve_token_out_list_response.py
swagger_client/models/approve_token_result.py
swagger_client/models/audit_info.py
swagger_client/models/contract_approve_response.py
swagger_client/models/contracts.py
swagger_client/models/contracts_security.py
swagger_client/models/dapp_contract_security_response.py
swagger_client/models/get_access_token_request.py
swagger_client/models/get_access_token_response.py
swagger_client/models/get_defi_info_response.py
swagger_client/models/get_defi_info_response_result.py
goplus-0.2.5.dist-info/METADATA
goplus-0.2.5.dist-info/WHEEL
goplus-0.2.5.dist-info/top_level.txt
goplus-0.2.5.dist-info/RECORD
